{
  "contact_email": "ops@jcprog.com",
  "version": "1.0",
  "sellers": [
    {
      "seller_id": "pub-3603488649",
      "seller_type": "PUBLISHER",
      "name": "Veraxen Ltd.",
      "domain": "veraxen.com"
    },
    {
      "seller_id": "pub-3396185247",
      "seller_type": "PUBLISHER",
      "name": "Odeeo",
      "domain": "odeeo.io"
    },
    {
      "seller_id": "pub-4192417344",
      "seller_type": "PUBLISHER",
      "name": "Bling Bling Games",
      "domain": "blingblinggames.com"
    },
    {
      "seller_id": "pub-9182148343",
      "seller_type": "PUBLISHER",
      "name": "Puzzle1Studio",
      "domain": "puzzle1studio.com"
    },
    {
      "seller_id": "pub-9261716889",
      "seller_type": "PUBLISHER",
      "name": "Incolor",
      "domain": "incolor.com"
    },
    {
      "seller_id": "pub-6014350992",
      "seller_type": "PUBLISHER",
      "name": "Hungry Studio",
      "domain": "hungrystudio.com"
    },
    {
      "seller_id": "pub-7089065334",
      "seller_type": "PUBLISHER",
      "name": "MobilityWare",
      "domain": "mobilityware.com"
    },
    {
      "seller_id": "pub-5935698367",
      "seller_type": "PUBLISHER",
      "name": "BitMango",
      "domain": "bitmango.com"
    },
    {
      "seller_id": "pub-3623870994",
      "seller_type": "PUBLISHER",
      "name": "Optime Software",
      "domain": "optimesoftware.com"
    },
    {
      "seller_id": "pub-6465839979",
      "seller_type": "PUBLISHER",
      "name": "Rubio Media LTD.",
      "domain": "rubio.ai"
    },
    {
      "seller_id": "pub-8904648557",
      "seller_type": "PUBLISHER",
      "name": "Blackout Lab",
      "domain": "blackout-lab.com"
    },
    {
      "seller_id": "pub-8557216340",
      "seller_type": "PUBLISHER",
      "name": "Uploss",
      "domain": "uploss.net"
    },
    {
      "seller_id": "pub-3212298323",
      "seller_type": "PUBLISHER",
      "name": "PeopleFun",
      "domain": "peoplefun.com"
    },
    {
      "seller_id": "pub-4518750432",
      "seller_type": "PUBLISHER",
      "name": "Unity Technologies",
      "domain": "unity.com"
    },
    {
      "seller_id": "pub-3791607228",
      "seller_type": "PUBLISHER",
      "name": "Musi Inc.",
      "domain": "musiapp.com"
    },
    {
      "seller_id": "pub-2397751667",
      "seller_type": "PUBLISHER",
      "name": "IEC Global Pty Ltd",
      "domain": "iecglobal.com.au"
    },
    {
      "seller_id": "pub-6597231902",
      "seller_type": "PUBLISHER",
      "name": "Wanda Cinemas Games",
      "domain": "wandacinemasgames.com"
    },
    {
      "seller_id": "pub-4502883373",
      "seller_type": "PUBLISHER",
      "name": "Gram Games",
      "domain": "gram.gs"
    },
    {
      "seller_id": "pub-6094257335",
      "seller_type": "PUBLISHER",
      "name": "RVN",
      "domain": "grouprvn.com"
    },
    {
      "seller_id": "pub-1865696947",
      "seller_type": "PUBLISHER",
      "name": "GeoTechnologies, Inc.",
      "domain": "geot.jp"
    },
    {
      "seller_id": "pub-8440963461",
      "seller_type": "PUBLISHER",
      "name": "Easybrain",
      "domain": "easybrain.com"
    },
    {
      "seller_id": "pub-6635876280",
      "seller_type": "PUBLISHER",
      "name": "Wattpad Corp.",
      "domain": "wattpad.com"
    },
    {
      "seller_id": "pub-4080251564",
      "seller_type": "PUBLISHER",
      "name": "Big Duck Games LLC",
      "domain": "bigduckgames.com"
    },
    {
      "seller_id": "pub-1571094057",
      "seller_type": "PUBLISHER",
      "name": "Rumble Inc.",
      "domain": "rumble.com"
    },
    {
      "seller_id": "pub-1908772970",
      "seller_type": "PUBLISHER",
      "name": "Binarystudio 54",
      "domain": "binarystudio54.com"
    },
    {
      "seller_id": "pub-3683894213",
      "seller_type": "PUBLISHER",
      "name": "Rejoy Studio",
      "domain": "rejoystudio.com"
    },
    {
      "seller_id": "pub-7585492221",
      "seller_type": "PUBLISHER",
      "name": "Brainium Studios",
      "domain": "brainium.com"
    }
  ]
}